[{"lemma":"ἀνακαινόω","form":"ᾰ̓νᾰκαινῶ","kind":"finite","tense":"present","voice":"active","mood":"indicative","number":"sg","person":"1sg"},{"lemma":"ἀνακαινόω","form":"ᾰ̓νᾰκαινῶ","kind":"finite","tense":"present","voice":"active","mood":"subjunctive","number":"sg","person":"1sg"},{"lemma":"ἀνακαινόω","form":"ᾰ̓νᾰκαινοῖς","kind":"finite","tense":"present","voice":"active","mood":"indicative","number":"sg","person":"2sg"},{"lemma":"ἀνακαινόω","form":"ᾰ̓νᾰκαινοῖς","kind":"finite","tense":"present","voice":"active","mood":"subjunctive","number":"sg","person":"2sg"},{"lemma":"ἀνακαινόω","form":"ᾰ̓νᾰκαινοῖς","kind":"finite","tense":"present","voice":"active","mood":"optative","number":"sg","person":"2sg"},{"lemma":"ἀνακαινόω","form":"ᾰ̓νᾰκαινοῖ","kind":"finite","tense":"present","voice":"active","mood":"indicative","number":"sg","person":"3sg"},{"lemma":"ἀνακαινόω","form":"ᾰ̓νᾰκαινοῖ","kind":"finite","tense":"present","voice":"active","mood":"subjunctive","number":"sg","person":"3sg"},{"lemma":"ἀνακαινόω","form":"ᾰ̓νᾰκαινοῖ","kind":"finite","tense":"present","voice":"active","mood":"optative","number":"sg","person":"3sg"},{"lemma":"ἀνακαινόω","form":"ᾰ̓νᾰκαινοῖ","kind":"finite","tense":"present","voice":"middle/passive","mood":"indicative","number":"sg","person":"2sg"},{"lemma":"ἀνακαινόω","form":"ᾰ̓νᾰκαινοῖ","kind":"finite","tense":"present","voice":"middle/passive","mood":"subjunctive","number":"sg","person":"2sg"},{"lemma":"ἀνακαινόω","form":"ᾰ̓νᾰκαινοῦτον","kind":"finite","tense":"present","voice":"active","mood":"indicative","number":"du","person":"2du"},{"lemma":"ἀνακαινόω","form":"ᾰ̓νᾰκαινοῦτον","kind":"finite","tense":"present","voice":"active","mood":"indicative","number":"du","person":"3du"},{"lemma":"ἀνακαινόω","form":"ᾰ̓νᾰκαινοῦτον","kind":"finite","tense":"present","voice":"active","mood":"imperative","number":"du","person":"2du"},{"lemma":"ἀνακαινόω","form":"ᾰ̓νᾰκαινοῦμεν","kind":"finite","tense":"present","voice":"active","mood":"indicative","number":"pl","person":"1sg"},{"lemma":"ἀνακαινόω","form":"ᾰ̓νᾰκαινοῦτε","kind":"finite","tense":"present","voice":"active","mood":"indicative","number":"pl","person":"2sg"},{"lemma":"ἀνακαινόω","form":"ᾰ̓νᾰκαινοῦτε","kind":"finite","tense":"present","voice":"active","mood":"imperative","number":"pl","person":"2sg"},{"lemma":"ἀνακαινόω","form":"ᾰ̓νᾰκαινοῦσῐ","kind":"finite","tense":"present","voice":"active","mood":"indicative","number":"pl","person":"3sg"},{"lemma":"ἀνακαινόω","form":"ᾰ̓νᾰκαινοῦσῐν","kind":"finite","tense":"present","voice":"active","mood":"indicative","number":"pl","person":"3sg"},{"lemma":"ἀνακαινόω","form":"ᾰ̓νᾰκαινῶτον","kind":"finite","tense":"present","voice":"active","mood":"subjunctive","number":"du","person":"2du"},{"lemma":"ἀνακαινόω","form":"ᾰ̓νᾰκαινῶτον","kind":"finite","tense":"present","voice":"active","mood":"subjunctive","number":"du","person":"3du"},{"lemma":"ἀνακαινόω","form":"ᾰ̓νᾰκαινῶμεν","kind":"finite","tense":"present","voice":"active","mood":"subjunctive","number":"pl","person":"1sg"},{"lemma":"ἀνακαινόω","form":"ᾰ̓νᾰκαινῶτε","kind":"finite","tense":"present","voice":"active","mood":"subjunctive","number":"pl","person":"2sg"},{"lemma":"ἀνακαινόω","form":"ᾰ̓νᾰκαινῶσῐ","kind":"finite","tense":"present","voice":"active","mood":"subjunctive","number":"pl","person":"3sg"},{"lemma":"ἀνακαινόω","form":"ᾰ̓νᾰκαινῶσῐν","kind":"finite","tense":"present","voice":"active","mood":"subjunctive","number":"pl","person":"3sg"},{"lemma":"ἀνακαινόω","form":"ᾰ̓νᾰκαινοίην","kind":"finite","tense":"present","voice":"active","mood":"optative","number":"sg","person":"1sg"},{"lemma":"ἀνακαινόω","form":"ᾰ̓νᾰκαινοῖμῐ","kind":"finite","tense":"present","voice":"active","mood":"optative","number":"sg","person":"1sg"},{"lemma":"ἀνακαινόω","form":"ᾰ̓νᾰκαινοίης","kind":"finite","tense":"present","voice":"active","mood":"optative","number":"sg","person":"2sg"},{"lemma":"ἀνακαινόω","form":"ᾰ̓νᾰκαινοίη","kind":"finite","tense":"present","voice":"active","mood":"optative","number":"sg","person":"3sg"},{"lemma":"ἀνακαινόω","form":"ᾰ̓νᾰκαινοῖτον","kind":"finite","tense":"present","voice":"active","mood":"optative","number":"du","person":"2du"},{"lemma":"ἀνακαινόω","form":"ᾰ̓νᾰκαινοίητον","kind":"finite","tense":"present","voice":"active","mood":"optative","number":"du","person":"2du"},{"lemma":"ἀνακαινόω","form":"ᾰ̓νᾰκαινοίτην","kind":"finite","tense":"present","voice":"active","mood":"optative","number":"du","person":"3du"},{"lemma":"ἀνακαινόω","form":"ᾰ̓νᾰκαινοιήτην","kind":"finite","tense":"present","voice":"active","mood":"optative","number":"du","person":"3du"},{"lemma":"ἀνακαινόω","form":"ᾰ̓νᾰκαινοῖμεν","kind":"finite","tense":"present","voice":"active","mood":"optative","number":"pl","person":"1sg"},{"lemma":"ἀνακαινόω","form":"ᾰ̓νᾰκαινοίημεν","kind":"finite","tense":"present","voice":"active","mood":"optative","number":"pl","person":"1sg"},{"lemma":"ἀνακαινόω","form":"ᾰ̓νᾰκαινοῖτε","kind":"finite","tense":"present","voice":"active","mood":"optative","number":"pl","person":"2sg"},{"lemma":"ἀνακαινόω","form":"ᾰ̓νᾰκαινοίητε","kind":"finite","tense":"present","voice":"active","mood":"optative","number":"pl","person":"2sg"},{"lemma":"ἀνακαινόω","form":"ᾰ̓νᾰκαινοῖεν","kind":"finite","tense":"present","voice":"active","mood":"optative","number":"pl","person":"3sg"},{"lemma":"ἀνακαινόω","form":"ᾰ̓νᾰκαινοίησᾰν","kind":"finite","tense":"present","voice":"active","mood":"optative","number":"pl","person":"3sg"},{"lemma":"ἀνακαινόω","form":"ᾰ̓νᾰκαίνου","kind":"finite","tense":"present","voice":"active","mood":"imperative","number":"sg","person":"2sg"},{"lemma":"ἀνακαινόω","form":"ᾰ̓νᾰκαινούτω","kind":"finite","tense":"present","voice":"active","mood":"imperative","number":"sg","person":"3sg"},{"lemma":"ἀνακαινόω","form":"ᾰ̓νᾰκαινούτων","kind":"finite","tense":"present","voice":"active","mood":"imperative","number":"du","person":"3du"},{"lemma":"ἀνακαινόω","form":"ᾰ̓νᾰκαινούντων","kind":"finite","tense":"present","voice":"active","mood":"imperative","number":"pl","person":"3sg"},{"lemma":"ἀνακαινόω","form":"ᾰ̓νᾰκαινοῦμαι","kind":"finite","tense":"present","voice":"middle/passive","mood":"indicative","number":"sg","person":"1sg"},{"lemma":"ἀνακαινόω","form":"ᾰ̓νᾰκαινοῦται","kind":"finite","tense":"present","voice":"middle/passive","mood":"indicative","number":"sg","person":"3sg"},{"lemma":"ἀνακαινόω","form":"ᾰ̓νᾰκαινοῦσθον","kind":"finite","tense":"present","voice":"middle/passive","mood":"indicative","number":"du","person":"2du"},{"lemma":"ἀνακαινόω","form":"ᾰ̓νᾰκαινοῦσθον","kind":"finite","tense":"present","voice":"middle/passive","mood":"indicative","number":"du","person":"3du"},{"lemma":"ἀνακαινόω","form":"ᾰ̓νᾰκαινοῦσθον","kind":"finite","tense":"present","voice":"middle/passive","mood":"imperative","number":"du","person":"2du"},{"lemma":"ἀνακαινόω","form":"ᾰ̓νᾰκαινούμεθᾰ","kind":"finite","tense":"present","voice":"middle/passive","mood":"indicative","number":"pl","person":"1sg"},{"lemma":"ἀνακαινόω","form":"ᾰ̓νᾰκαινοῦσθε","kind":"finite","tense":"present","voice":"middle/passive","mood":"indicative","number":"pl","person":"2sg"},{"lemma":"ἀνακαινόω","form":"ᾰ̓νᾰκαινοῦσθε","kind":"finite","tense":"present","voice":"middle/passive","mood":"imperative","number":"pl","person":"2sg"},{"lemma":"ἀνακαινόω","form":"ᾰ̓νᾰκαινοῦνται","kind":"finite","tense":"present","voice":"middle/passive","mood":"indicative","number":"pl","person":"3sg"},{"lemma":"ἀνακαινόω","form":"ᾰ̓νᾰκαινῶμαι","kind":"finite","tense":"present","voice":"middle/passive","mood":"subjunctive","number":"sg","person":"1sg"},{"lemma":"ἀνακαινόω","form":"ᾰ̓νᾰκαινῶται","kind":"finite","tense":"present","voice":"middle/passive","mood":"subjunctive","number":"sg","person":"3sg"},{"lemma":"ἀνακαινόω","form":"ᾰ̓νᾰκαινῶσθον","kind":"finite","tense":"present","voice":"middle/passive","mood":"subjunctive","number":"du","person":"2du"},{"lemma":"ἀνακαινόω","form":"ᾰ̓νᾰκαινῶσθον","kind":"finite","tense":"present","voice":"middle/passive","mood":"subjunctive","number":"du","person":"3du"},{"lemma":"ἀνακαινόω","form":"ᾰ̓νᾰκαινώμεθᾰ","kind":"finite","tense":"present","voice":"middle/passive","mood":"subjunctive","number":"pl","person":"1sg"},{"lemma":"ἀνακαινόω","form":"ᾰ̓νᾰκαινῶσθε","kind":"finite","tense":"present","voice":"middle/passive","mood":"subjunctive","number":"pl","person":"2sg"},{"lemma":"ἀνακαινόω","form":"ᾰ̓νᾰκαινῶνται","kind":"finite","tense":"present","voice":"middle/passive","mood":"subjunctive","number":"pl","person":"3sg"},{"lemma":"ἀνακαινόω","form":"ᾰ̓νᾰκαινοίμην","kind":"finite","tense":"present","voice":"middle/passive","mood":"optative","number":"sg","person":"1sg"},{"lemma":"ἀνακαινόω","form":"ᾰ̓νᾰκαινοῖο","kind":"finite","tense":"present","voice":"middle/passive","mood":"optative","number":"sg","person":"2sg"},{"lemma":"ἀνακαινόω","form":"ᾰ̓νᾰκαινοῖτο","kind":"finite","tense":"present","voice":"middle/passive","mood":"optative","number":"sg","person":"3sg"},{"lemma":"ἀνακαινόω","form":"ᾰ̓νᾰκαινοῖσθον","kind":"finite","tense":"present","voice":"middle/passive","mood":"optative","number":"du","person":"2du"},{"lemma":"ἀνακαινόω","form":"ᾰ̓νᾰκαινοίσθην","kind":"finite","tense":"present","voice":"middle/passive","mood":"optative","number":"du","person":"3du"},{"lemma":"ἀνακαινόω","form":"ᾰ̓νᾰκαινοίμεθᾰ","kind":"finite","tense":"present","voice":"middle/passive","mood":"optative","number":"pl","person":"1sg"},{"lemma":"ἀνακαινόω","form":"ᾰ̓νᾰκαινοῖσθε","kind":"finite","tense":"present","voice":"middle/passive","mood":"optative","number":"pl","person":"2sg"},{"lemma":"ἀνακαινόω","form":"ᾰ̓νᾰκαινοῖντο","kind":"finite","tense":"present","voice":"middle/passive","mood":"optative","number":"pl","person":"3sg"},{"lemma":"ἀνακαινόω","form":"ᾰ̓νᾰκαινοῦ","kind":"finite","tense":"present","voice":"middle/passive","mood":"imperative","number":"sg","person":"2sg"},{"lemma":"ἀνακαινόω","form":"ᾰ̓νᾰκαινούσθω","kind":"finite","tense":"present","voice":"middle/passive","mood":"imperative","number":"sg","person":"3sg"},{"lemma":"ἀνακαινόω","form":"ᾰ̓νᾰκαινούσθων","kind":"finite","tense":"present","voice":"middle/passive","mood":"imperative","number":"du","person":"3du"},{"lemma":"ἀνακαινόω","form":"ᾰ̓νᾰκαινούσθων","kind":"finite","tense":"present","voice":"middle/passive","mood":"imperative","number":"pl","person":"3sg"},{"lemma":"ἀνακαινόω","form":"ᾰ̓νᾰκαινοῦν","kind":"infinitive","tense":"present","voice":"active","mood":"infinitive"},{"lemma":"ἀνακαινόω","form":"ᾰ̓νᾰκαινοῦν","kind":"participle","tense":"present","voice":"active","mood":"participle","gender":"neut"},{"lemma":"ἀνακαινόω","form":"ᾰ̓νᾰκαινοῦσθαι","kind":"infinitive","tense":"present","voice":"middle/passive","mood":"infinitive"},{"lemma":"ἀνακαινόω","form":"ᾰ̓νᾰκαινῶν","kind":"participle","tense":"present","voice":"active","mood":"participle","gender":"masc"},{"lemma":"ἀνακαινόω","form":"ᾰ̓νᾰκαινούμενος","kind":"participle","tense":"present","voice":"middle/passive","mood":"participle","gender":"masc"},{"lemma":"ἀνακαινόω","form":"ᾰ̓νᾰκαινοῦσᾰ","kind":"participle","tense":"present","voice":"active","mood":"participle","gender":"fem"},{"lemma":"ἀνακαινόω","form":"ᾰ̓νᾰκαινουμένη","kind":"participle","tense":"present","voice":"middle/passive","mood":"participle","gender":"fem"},{"lemma":"ἀνακαινόω","form":"ᾰ̓νᾰκαινούμενον","kind":"participle","tense":"present","voice":"middle/passive","mood":"participle","gender":"neut"},{"lemma":"ἀνακαινόω","form":"ᾰ̓νεκαίνουν","kind":"finite","tense":"imperfect","voice":"active","mood":"indicative","number":"sg","person":"1sg"},{"lemma":"ἀνακαινόω","form":"ᾰ̓νεκαίνουν","kind":"finite","tense":"imperfect","voice":"active","mood":"indicative","number":"pl","person":"3sg"},{"lemma":"ἀνακαινόω","form":"ᾰ̓νεκαίνους","kind":"finite","tense":"imperfect","voice":"active","mood":"indicative","number":"sg","person":"2sg"},{"lemma":"ἀνακαινόω","form":"ᾰ̓νεκαίνου","kind":"finite","tense":"imperfect","voice":"active","mood":"indicative","number":"sg","person":"3sg"},{"lemma":"ἀνακαινόω","form":"ᾰ̓νεκαινοῦτον","kind":"finite","tense":"imperfect","voice":"active","mood":"indicative","number":"du","person":"2du"},{"lemma":"ἀνακαινόω","form":"ᾰ̓νεκαινούτην","kind":"finite","tense":"imperfect","voice":"active","mood":"indicative","number":"du","person":"3du"},{"lemma":"ἀνακαινόω","form":"ᾰ̓νεκαινοῦμεν","kind":"finite","tense":"imperfect","voice":"active","mood":"indicative","number":"pl","person":"1sg"},{"lemma":"ἀνακαινόω","form":"ᾰ̓νεκαινοῦτε","kind":"finite","tense":"imperfect","voice":"active","mood":"indicative","number":"pl","person":"2sg"},{"lemma":"ἀνακαινόω","form":"ᾰ̓νεκαινούμην","kind":"finite","tense":"imperfect","voice":"middle/passive","mood":"indicative","number":"sg","person":"1sg"},{"lemma":"ἀνακαινόω","form":"ᾰ̓νεκαινοῦ","kind":"finite","tense":"imperfect","voice":"middle/passive","mood":"indicative","number":"sg","person":"2sg"},{"lemma":"ἀνακαινόω","form":"ᾰ̓νεκαινοῦτο","kind":"finite","tense":"imperfect","voice":"middle/passive","mood":"indicative","number":"sg","person":"3sg"},{"lemma":"ἀνακαινόω","form":"ᾰ̓νεκαινοῦσθον","kind":"finite","tense":"imperfect","voice":"middle/passive","mood":"indicative","number":"du","person":"2du"},{"lemma":"ἀνακαινόω","form":"ᾰ̓νεκαινούσθην","kind":"finite","tense":"imperfect","voice":"middle/passive","mood":"indicative","number":"du","person":"3du"},{"lemma":"ἀνακαινόω","form":"ᾰ̓νεκαινούμεθᾰ","kind":"finite","tense":"imperfect","voice":"middle/passive","mood":"indicative","number":"pl","person":"1sg"},{"lemma":"ἀνακαινόω","form":"ᾰ̓νεκαινοῦσθε","kind":"finite","tense":"imperfect","voice":"middle/passive","mood":"indicative","number":"pl","person":"2sg"},{"lemma":"ἀνακαινόω","form":"ᾰ̓νεκαινοῦντο","kind":"finite","tense":"imperfect","voice":"middle/passive","mood":"indicative","number":"pl","person":"3sg"},{"lemma":"ἀνακαινόω","form":"ᾰ̓νεκαίνωσᾰ","kind":"finite","tense":"aorist","voice":"active","mood":"indicative","number":"sg","person":"1sg"},{"lemma":"ἀνακαινόω","form":"ᾰ̓νεκαίνωσᾰς","kind":"finite","tense":"aorist","voice":"active","mood":"indicative","number":"sg","person":"2sg"},{"lemma":"ἀνακαινόω","form":"ᾰ̓νεκαίνωσε","kind":"finite","tense":"aorist","voice":"active","mood":"indicative","number":"sg","person":"3sg"},{"lemma":"ἀνακαινόω","form":"ᾰ̓νεκαίνωσεν","kind":"finite","tense":"aorist","voice":"active","mood":"indicative","number":"sg","person":"3sg"},{"lemma":"ἀνακαινόω","form":"ᾰ̓νεκαινώσᾰτον","kind":"finite","tense":"aorist","voice":"active","mood":"indicative","number":"du","person":"2du"},{"lemma":"ἀνακαινόω","form":"ᾰ̓νεκαινωσᾰ́την","kind":"finite","tense":"aorist","voice":"active","mood":"indicative","number":"du","person":"3du"},{"lemma":"ἀνακαινόω","form":"ᾰ̓νεκαινώσᾰμεν","kind":"finite","tense":"aorist","voice":"active","mood":"indicative","number":"pl","person":"1sg"},{"lemma":"ἀνακαινόω","form":"ᾰ̓νεκαινώσᾰτε","kind":"finite","tense":"aorist","voice":"active","mood":"indicative","number":"pl","person":"2sg"},{"lemma":"ἀνακαινόω","form":"ᾰ̓νεκαίνωσᾰν","kind":"finite","tense":"aorist","voice":"active","mood":"indicative","number":"pl","person":"3sg"},{"lemma":"ἀνακαινόω","form":"ᾰ̓νᾰκαινώσω","kind":"finite","tense":"aorist","voice":"active","mood":"subjunctive","number":"sg","person":"1sg"},{"lemma":"ἀνακαινόω","form":"ᾰ̓νᾰκαινώσῃς","kind":"finite","tense":"aorist","voice":"active","mood":"subjunctive","number":"sg","person":"2sg"},{"lemma":"ἀνακαινόω","form":"ᾰ̓νᾰκαινώσῃ","kind":"finite","tense":"aorist","voice":"active","mood":"subjunctive","number":"sg","person":"3sg"},{"lemma":"ἀνακαινόω","form":"ᾰ̓νᾰκαινώσητον","kind":"finite","tense":"aorist","voice":"active","mood":"subjunctive","number":"du","person":"2du"},{"lemma":"ἀνακαινόω","form":"ᾰ̓νᾰκαινώσητον","kind":"finite","tense":"aorist","voice":"active","mood":"subjunctive","number":"du","person":"3du"},{"lemma":"ἀνακαινόω","form":"ᾰ̓νᾰκαινώσωμεν","kind":"finite","tense":"aorist","voice":"active","mood":"subjunctive","number":"pl","person":"1sg"},{"lemma":"ἀνακαινόω","form":"ᾰ̓νᾰκαινώσητε","kind":"finite","tense":"aorist","voice":"active","mood":"subjunctive","number":"pl","person":"2sg"},{"lemma":"ἀνακαινόω","form":"ᾰ̓νᾰκαινώσωσῐ","kind":"finite","tense":"aorist","voice":"active","mood":"subjunctive","number":"pl","person":"3sg"},{"lemma":"ἀνακαινόω","form":"ᾰ̓νᾰκαινώσωσῐν","kind":"finite","tense":"aorist","voice":"active","mood":"subjunctive","number":"pl","person":"3sg"},{"lemma":"ἀνακαινόω","form":"ᾰ̓νᾰκαινώσαιμῐ","kind":"finite","tense":"aorist","voice":"active","mood":"optative","number":"sg","person":"1sg"},{"lemma":"ἀνακαινόω","form":"ᾰ̓νᾰκαινώσειᾰς","kind":"finite","tense":"aorist","voice":"active","mood":"optative","number":"sg","person":"2sg"},{"lemma":"ἀνακαινόω","form":"ᾰ̓νᾰκαινώσαις","kind":"finite","tense":"aorist","voice":"active","mood":"optative","number":"sg","person":"2sg"},{"lemma":"ἀνακαινόω","form":"ᾰ̓νᾰκαινώσειε","kind":"finite","tense":"aorist","voice":"active","mood":"optative","number":"sg","person":"3sg"},{"lemma":"ἀνακαινόω","form":"ᾰ̓νᾰκαινώσειεν","kind":"finite","tense":"aorist","voice":"active","mood":"optative","number":"sg","person":"3sg"},{"lemma":"ἀνακαινόω","form":"ᾰ̓νᾰκαινώσαι","kind":"finite","tense":"aorist","voice":"active","mood":"optative","number":"sg","person":"3sg"},{"lemma":"ἀνακαινόω","form":"ᾰ̓νᾰκαινώσαιτον","kind":"finite","tense":"aorist","voice":"active","mood":"optative","number":"du","person":"2du"},{"lemma":"ἀνακαινόω","form":"ᾰ̓νᾰκαινωσαίτην","kind":"finite","tense":"aorist","voice":"active","mood":"optative","number":"du","person":"3du"},{"lemma":"ἀνακαινόω","form":"ᾰ̓νᾰκαινώσαιμεν","kind":"finite","tense":"aorist","voice":"active","mood":"optative","number":"pl","person":"1sg"},{"lemma":"ἀνακαινόω","form":"ᾰ̓νᾰκαινώσαιτε","kind":"finite","tense":"aorist","voice":"active","mood":"optative","number":"pl","person":"2sg"},{"lemma":"ἀνακαινόω","form":"ᾰ̓νᾰκαινώσειᾰν","kind":"finite","tense":"aorist","voice":"active","mood":"optative","number":"pl","person":"3sg"},{"lemma":"ἀνακαινόω","form":"ᾰ̓νᾰκαινώσαιεν","kind":"finite","tense":"aorist","voice":"active","mood":"optative","number":"pl","person":"3sg"},{"lemma":"ἀνακαινόω","form":"ᾰ̓νᾰκαίνωσον","kind":"finite","tense":"aorist","voice":"active","mood":"imperative","number":"sg","person":"2sg"},{"lemma":"ἀνακαινόω","form":"ᾰ̓νᾰκαινωσᾰ́τω","kind":"finite","tense":"aorist","voice":"active","mood":"imperative","number":"sg","person":"3sg"},{"lemma":"ἀνακαινόω","form":"ᾰ̓νᾰκαινώσᾰτον","kind":"finite","tense":"aorist","voice":"active","mood":"imperative","number":"du","person":"2du"},{"lemma":"ἀνακαινόω","form":"ᾰ̓νᾰκαινωσᾰ́των","kind":"finite","tense":"aorist","voice":"active","mood":"imperative","number":"du","person":"3du"},{"lemma":"ἀνακαινόω","form":"ᾰ̓νᾰκαινώσᾰτε","kind":"finite","tense":"aorist","voice":"active","mood":"imperative","number":"pl","person":"2sg"},{"lemma":"ἀνακαινόω","form":"ᾰ̓νᾰκαινωσᾰ́ντων","kind":"finite","tense":"aorist","voice":"active","mood":"imperative","number":"pl","person":"3sg"},{"lemma":"ἀνακαινόω","form":"ᾰ̓νᾰκαινῶσαι","kind":"infinitive","tense":"aorist","voice":"active","mood":"infinitive"},{"lemma":"ἀνακαινόω","form":"ᾰ̓νᾰκαινώσᾱς","kind":"participle","tense":"aorist","voice":"active","mood":"participle","gender":"masc"},{"lemma":"ἀνακαινόω","form":"ᾰ̓νᾰκαινώσᾱσᾰ","kind":"participle","tense":"aorist","voice":"active","mood":"participle","gender":"fem"},{"lemma":"ἀνακαινόω","form":"ᾰ̓νᾰκαινῶσᾰν","kind":"participle","tense":"aorist","voice":"active","mood":"participle","gender":"neut"},{"lemma":"ἀνακαινόω","form":"ᾰ̓νᾰκεκαίνωμαι","kind":"finite","tense":"perfect","voice":"middle/passive","mood":"indicative","number":"sg","person":"1sg"},{"lemma":"ἀνακαινόω","form":"ᾰ̓νᾰκεκαίνωσαι","kind":"finite","tense":"perfect","voice":"middle/passive","mood":"indicative","number":"sg","person":"2sg"},{"lemma":"ἀνακαινόω","form":"ᾰ̓νᾰκεκαίνωται","kind":"finite","tense":"perfect","voice":"middle/passive","mood":"indicative","number":"sg","person":"3sg"},{"lemma":"ἀνακαινόω","form":"ᾰ̓νᾰκεκαίνωσθον","kind":"finite","tense":"perfect","voice":"middle/passive","mood":"indicative","number":"du","person":"2du"},{"lemma":"ἀνακαινόω","form":"ᾰ̓νᾰκεκαίνωσθον","kind":"finite","tense":"perfect","voice":"middle/passive","mood":"indicative","number":"du","person":"3du"},{"lemma":"ἀνακαινόω","form":"ᾰ̓νᾰκεκαίνωσθον","kind":"finite","tense":"perfect","voice":"middle/passive","mood":"imperative","number":"du","person":"2du"},{"lemma":"ἀνακαινόω","form":"ᾰ̓νᾰκεκαινώμεθᾰ","kind":"finite","tense":"perfect","voice":"middle/passive","mood":"indicative","number":"pl","person":"1sg"},{"lemma":"ἀνακαινόω","form":"ᾰ̓νᾰκεκαίνωσθε","kind":"finite","tense":"perfect","voice":"middle/passive","mood":"indicative","number":"pl","person":"2sg"},{"lemma":"ἀνακαινόω","form":"ᾰ̓νᾰκεκαίνωσθε","kind":"finite","tense":"perfect","voice":"middle/passive","mood":"imperative","number":"pl","person":"2sg"},{"lemma":"ἀνακαινόω","form":"ᾰ̓νᾰκεκαίνωνται","kind":"finite","tense":"perfect","voice":"middle/passive","mood":"indicative","number":"pl","person":"3sg"},{"lemma":"ἀνακαινόω","form":"ᾰ̓νᾰκεκαινωμένος ὦ","kind":"finite","tense":"perfect","voice":"middle/passive","mood":"subjunctive","number":"sg","person":"1sg"},{"lemma":"ἀνακαινόω","form":"ᾰ̓νᾰκεκαινωμένος ᾖς","kind":"finite","tense":"perfect","voice":"middle/passive","mood":"subjunctive","number":"sg","person":"2sg"},{"lemma":"ἀνακαινόω","form":"ᾰ̓νᾰκεκαινωμένος ᾖ","kind":"finite","tense":"perfect","voice":"middle/passive","mood":"subjunctive","number":"sg","person":"3sg"},{"lemma":"ἀνακαινόω","form":"ᾰ̓νᾰκεκαινωμένω ἦτον","kind":"finite","tense":"perfect","voice":"middle/passive","mood":"subjunctive","number":"du","person":"2du"},{"lemma":"ἀνακαινόω","form":"ᾰ̓νᾰκεκαινωμένω ἦτον","kind":"finite","tense":"perfect","voice":"middle/passive","mood":"subjunctive","number":"du","person":"3du"},{"lemma":"ἀνακαινόω","form":"ᾰ̓νᾰκεκαινωμένοι ὦμεν","kind":"finite","tense":"perfect","voice":"middle/passive","mood":"subjunctive","number":"pl","person":"1sg"},{"lemma":"ἀνακαινόω","form":"ᾰ̓νᾰκεκαινωμένοι ἦτε","kind":"finite","tense":"perfect","voice":"middle/passive","mood":"subjunctive","number":"pl","person":"2sg"},{"lemma":"ἀνακαινόω","form":"ᾰ̓νᾰκεκαινωμένοι ὦσῐ","kind":"finite","tense":"perfect","voice":"middle/passive","mood":"subjunctive","number":"pl","person":"3sg"},{"lemma":"ἀνακαινόω","form":"ᾰ̓νᾰκεκαινωμένοι ὦσῐν","kind":"finite","tense":"perfect","voice":"middle/passive","mood":"subjunctive","number":"pl","person":"3sg"},{"lemma":"ἀνακαινόω","form":"ᾰ̓νᾰκεκαινωμένος εἴην","kind":"finite","tense":"perfect","voice":"middle/passive","mood":"optative","number":"sg","person":"1sg"},{"lemma":"ἀνακαινόω","form":"ᾰ̓νᾰκεκαινωμένος εἴης","kind":"finite","tense":"perfect","voice":"middle/passive","mood":"optative","number":"sg","person":"2sg"},{"lemma":"ἀνακαινόω","form":"ᾰ̓νᾰκεκαινωμένος εἴη","kind":"finite","tense":"perfect","voice":"middle/passive","mood":"optative","number":"sg","person":"3sg"},{"lemma":"ἀνακαινόω","form":"ᾰ̓νᾰκεκαινωμένοι εἴητον","kind":"finite","tense":"perfect","voice":"middle/passive","mood":"optative","number":"du","person":"2du"},{"lemma":"ἀνακαινόω","form":"ᾰ̓νᾰκεκαινωμένοι εἶτον","kind":"finite","tense":"perfect","voice":"middle/passive","mood":"optative","number":"du","person":"2du"},{"lemma":"ἀνακαινόω","form":"ᾰ̓νᾰκεκαινωμένω εἰήτην","kind":"finite","tense":"perfect","voice":"middle/passive","mood":"optative","number":"du","person":"3du"},{"lemma":"ἀνακαινόω","form":"ᾰ̓νᾰκεκαινωμένω εἴτην","kind":"finite","tense":"perfect","voice":"middle/passive","mood":"optative","number":"du","person":"3du"},{"lemma":"ἀνακαινόω","form":"ᾰ̓νᾰκεκαινωμένοι εἴημεν","kind":"finite","tense":"perfect","voice":"middle/passive","mood":"optative","number":"pl","person":"1sg"},{"lemma":"ἀνακαινόω","form":"ᾰ̓νᾰκεκαινωμένοι εἶμεν","kind":"finite","tense":"perfect","voice":"middle/passive","mood":"optative","number":"pl","person":"1sg"},{"lemma":"ἀνακαινόω","form":"ᾰ̓νᾰκεκαινωμένοι εἴητε","kind":"finite","tense":"perfect","voice":"middle/passive","mood":"optative","number":"pl","person":"2sg"},{"lemma":"ἀνακαινόω","form":"ᾰ̓νᾰκεκαινωμένοι εἶτε","kind":"finite","tense":"perfect","voice":"middle/passive","mood":"optative","number":"pl","person":"2sg"},{"lemma":"ἀνακαινόω","form":"ᾰ̓νᾰκεκαινωμένοι εἴησᾰν","kind":"finite","tense":"perfect","voice":"middle/passive","mood":"optative","number":"pl","person":"3sg"},{"lemma":"ἀνακαινόω","form":"ᾰ̓νᾰκεκαινωμένοι εἶεν","kind":"finite","tense":"perfect","voice":"middle/passive","mood":"optative","number":"pl","person":"3sg"},{"lemma":"ἀνακαινόω","form":"ᾰ̓νᾰκεκαίνωσο","kind":"finite","tense":"perfect","voice":"middle/passive","mood":"imperative","number":"sg","person":"2sg"},{"lemma":"ἀνακαινόω","form":"ᾰ̓νᾰκεκαινώσθω","kind":"finite","tense":"perfect","voice":"middle/passive","mood":"imperative","number":"sg","person":"3sg"},{"lemma":"ἀνακαινόω","form":"ᾰ̓νᾰκεκαινώσθων","kind":"finite","tense":"perfect","voice":"middle/passive","mood":"imperative","number":"du","person":"3du"},{"lemma":"ἀνακαινόω","form":"ᾰ̓νᾰκεκαινώσθων","kind":"finite","tense":"perfect","voice":"middle/passive","mood":"imperative","number":"pl","person":"3sg"},{"lemma":"ἀνακαινόω","form":"ᾰ̓νᾰκεκαινῶσθαι","kind":"infinitive","tense":"perfect","voice":"middle/passive","mood":"infinitive"},{"lemma":"ἀνακαινόω","form":"ᾰ̓νᾰκεκαινωμένος","kind":"participle","tense":"perfect","voice":"middle/passive","mood":"participle","gender":"masc"},{"lemma":"ἀνακαινόω","form":"ᾰ̓νᾰκεκαινωμένη","kind":"participle","tense":"perfect","voice":"middle/passive","mood":"participle","gender":"fem"},{"lemma":"ἀνακαινόω","form":"ᾰ̓νᾰκεκαινωμένον","kind":"participle","tense":"perfect","voice":"middle/passive","mood":"participle","gender":"neut"}]